acr/__init__.py
acr/__main__.py
acr/cli.py
acr/commands/__init__.py
acr/commands/install.py
acr/commands/install_helpers.py
acr/commands/review.py
acr/configuration.py
acr/core/__init__.py
acr/core/analyzer.py
acr/core/git_utils.py
acr/core/models.py
acr/utils/__init__.py
acr/utils/config_manager.py
acr/utils/helpers.py
acr/utils/output.py
acr_cli-0.2.6.dist-info/entry_points.txt
acr_cli-0.2.6.dist-info/LICENSE
acr_cli-0.2.6.dist-info/METADATA
acr_cli-0.2.6.dist-info/WHEEL
acr_cli-0.2.6.dist-info/RECORD
