Metadata-Version: 2.3
Name: acr-cli
Version: 0.2.6
Summary: ACR - Automated Code Review
Author: inksne
Author-email: inksne@gmail.com
Requires-Python: >=3.9
Classifier: Programming Language :: Python :: 3
Classifier: Programming Language :: Python :: 3.9
Classifier: Programming Language :: Python :: 3.10
Classifier: Programming Language :: Python :: 3.11
Classifier: Programming Language :: Python :: 3.12
Classifier: Programming Language :: Python :: 3.13
Requires-Dist: gitpython (>=3.1.45,<4.0.0)
Requires-Dist: pytest (>=8.4.2,<9.0.0)
Requires-Dist: pyyaml (>=6.0.3,<7.0.0)
Requires-Dist: rich (==14.1.0)
Requires-Dist: typer (>=0.19.2,<0.20.0)
Requires-Dist: types-pyyaml (>=6.0.12.20250915,<7.0.0.0)
